jenkins_mcp_enterprise/__init__.py
jenkins_mcp_enterprise/base.py
jenkins_mcp_enterprise/cache_manager.py
jenkins_mcp_enterprise/cleanup_manager.py
jenkins_mcp_enterprise/cli.py
jenkins_mcp_enterprise/config.py
jenkins_mcp_enterprise/config_factory.py
jenkins_mcp_enterprise/di_container.py
jenkins_mcp_enterprise/exceptions.py
jenkins_mcp_enterprise/http_server.py
jenkins_mcp_enterprise/logging_config.py
jenkins_mcp_enterprise/multi_jenkins_manager.py
jenkins_mcp_enterprise/retry_utils.py
jenkins_mcp_enterprise/server.py
jenkins_mcp_enterprise/tool_factory.py
jenkins_mcp_enterprise/tool_validator.py
jenkins_mcp_enterprise/utils.py
jenkins_mcp_enterprise/vector_manager.py
jenkins_mcp_enterprise/diagnostic_config/__init__.py
jenkins_mcp_enterprise/diagnostic_config/diagnostic-parameters.yml
jenkins_mcp_enterprise/diagnostic_config/diagnostic_config.py
jenkins_mcp_enterprise/jenkins/__init__.py
jenkins_mcp_enterprise/jenkins/build_manager.py
jenkins_mcp_enterprise/jenkins/connection_manager.py
jenkins_mcp_enterprise/jenkins/jenkins_client.py
jenkins_mcp_enterprise/jenkins/job_name_utils.py
jenkins_mcp_enterprise/jenkins/log_fetcher.py
jenkins_mcp_enterprise/jenkins/subbuild_discoverer.py
jenkins_mcp_enterprise/llm/__init__.py
jenkins_mcp_enterprise/streaming/__init__.py
jenkins_mcp_enterprise/streaming/log_processor.py
jenkins_mcp_enterprise/tools/__init__.py
jenkins_mcp_enterprise/tools/base_tools.py
jenkins_mcp_enterprise/tools/common.py
jenkins_mcp_enterprise/tools/diagnostics.py
jenkins_mcp_enterprise/tools/jenkins_tools.py
jenkins_mcp_enterprise/tools/logs.py
jenkins_mcp_enterprise/tools/ripgrep_tool.py
jenkins_mcp_enterprise/tools/search.py
jenkins_mcp_enterprise/tools/subbuilds.py
jenkins_mcp_enterprise/tools/trigger.py
mseep_jenkins_mcp_enterprise-1.0.4.dist-info/licenses/LICENSE
mseep_jenkins_mcp_enterprise-1.0.4.dist-info/METADATA
mseep_jenkins_mcp_enterprise-1.0.4.dist-info/WHEEL
mseep_jenkins_mcp_enterprise-1.0.4.dist-info/entry_points.txt
mseep_jenkins_mcp_enterprise-1.0.4.dist-info/top_level.txt
mseep_jenkins_mcp_enterprise-1.0.4.dist-info/RECORD
